{"_id":{"$oid":"5c43cb1d6fd76d1de0601df3"},"title":"黄瓜"}
{"_id":{"$oid":"5c43cb276fd76d1de0601df4"},"title":"瓜"}
{"_id":{"$oid":"5c43cb366fd76d1de0601df5"},"title":"参"}
{"_id":{"$oid":"5c43ce7af9c3721fb4833e24"},"title":"黄"}
{"_id":{"$oid":"5c43cfddf9c3721fb4833e25"},"title":"地瓜"}
{"_id":{"$oid":"5c43d2b1f9c3721fb4833e26"},"title":"无籽西瓜"}
{"_id":{"$oid":"5c43eda75613e52da83cde52"},"title":"苦瓜"}
{"_id":{"$oid":"5c43ef315613e52da83cde53"},"title":"无花果"}
{"_id":{"$oid":"5c43f0295613e52da83cde54"},"title":"哈密瓜"}
